dooit_extras/bar_widgets/__init__.py
dooit_extras/bar_widgets/_base.py
dooit_extras/bar_widgets/clock.py
dooit_extras/bar_widgets/current_workspace.py
dooit_extras/bar_widgets/date.py
dooit_extras/bar_widgets/mode.py
dooit_extras/bar_widgets/platform.py
dooit_extras/bar_widgets/powerline.py
dooit_extras/bar_widgets/spacer.py
dooit_extras/bar_widgets/status_icons.py
dooit_extras/bar_widgets/text_box.py
dooit_extras/bar_widgets/text_poller.py
dooit_extras/bar_widgets/ticker.py
dooit_extras/bar_widgets/workspace_progress.py
dooit_extras/formatters/__init__.py
dooit_extras/formatters/description.py
dooit_extras/formatters/due.py
dooit_extras/formatters/effort.py
dooit_extras/formatters/recurrence.py
dooit_extras/formatters/status.py
dooit_extras/formatters/urgency.py
dooit_extras/scripts/__init__.py
dooit_extras/scripts/custom_tree_borders.py
dooit_extras/scripts/dim_unfocused.py
dooit_extras/scripts/toggle_workspaces.py
dooit_extras-0.2.1.dist-info/LICENSE
dooit_extras-0.2.1.dist-info/METADATA
dooit_extras-0.2.1.dist-info/WHEEL
dooit_extras-0.2.1.dist-info/RECORD
