Metadata-Version: 2.3
Name: dooit-extras
Version: 0.2.1
Summary: A collection of utilities to customize your dooit!
License: MIT
Author: kraanzu
Author-email: kraanzu@gmail.com
Requires-Python: >=3.9,<4.0
Classifier: License :: OSI Approved :: MIT License
Classifier: Programming Language :: Python :: 3
Classifier: Programming Language :: Python :: 3.9
Classifier: Programming Language :: Python :: 3.10
Classifier: Programming Language :: Python :: 3.11
Classifier: Programming Language :: Python :: 3.12
Classifier: Programming Language :: Python :: 3.13
Requires-Dist: dooit (>=3.2.2,<4.0.0)
